{
  "articles": [
    {
      "author": "BuzzFeed Shopping",
      "content": "Promising reviews: \"Works like magic. Inexpensive, so obviously not top of the line stuff, but gets the job done.\" S.I.\"Okay, so first, nothing will make you 'poreless,' but this stuff is amazing. Wi\u2026 [+459 chars]",
      "description": "You're welcome.",
      "publishedAt": "2023-10-24T09:45:26Z",
      "source": {
        "id": "the-huffington-post",
        "name": "The Huffington Post"
      },
      "title": "39 Beauty Products From Amazon People Are Loving In 2023 So Far",
      "url": "https://www.huffpost.com/entry/39-beauty-products-from-amazon-people-are-loving-in-2023-so-far_l_6532774ce4b0eb7cdbc26d79",
      "urlToImage": "https://img.huffingtonpost.com/asset/65327940230000fb0854ab0d.png?ops=1200_630"
    },
    {
      "author": "Buzzfeed Shopping",
      "content": "Made with an easy-release, silicone-based nonstick coating. The pan is dishwasher-safe, but hand-washing is recommended to extend product life.Promising review: \"We already use several Chicago Metall\u2026 [+488 chars]",
      "description": "Don't worry \u2014 you'll own some of these soon.",
      "publishedAt": "2023-10-24T09:45:26Z",
      "source": {
        "id": "the-huffington-post",
        "name": "The Huffington Post"
      },
      "title": "26 Kitchen Products That'll Make You Think, \"Why Didn't I Own That Already\"",
      "url": "https://www.huffpost.com/entry/kitchen-products-you-need-goog_l_6532b859e4b011a9cf798018",
      "urlToImage": "https://img.huffingtonpost.com/asset/641d1ea223000074004b5976.png?cache=n7j8m9J6ei&ops=1200_630"
    },
    {
      "author": "BuzzFeed Shopping",
      "content": "Promising reviews: \"Day to night, this dress the perfect transition dress. Good thick material, adjustable straps, little side slits. I did size up to a large because I wanted a looser fit.\" Kalyn\"I \u2026 [+383 chars]",
      "description": "It's elegance, it's ease, it's... not a phase, Mom.",
      "publishedAt": "2023-10-24T09:45:26Z",
      "source": {
        "id": "the-huffington-post",
        "name": "The Huffington Post"
      },
      "title": "If You Refuse To Wear Anything Other Than Black, You Need These 38 Fashion Pieces In Your Closet",
      "url": "https://www.huffpost.com/entry/chic-black-clothing-for-women-ano_l_6532bc26e4b0689b3fbc6c07",
      "urlToImage": "https://img.huffingtonpost.com/asset/6515f2ce220000200006ec88.png?cache=VWDgga1eZW&ops=1200_630"
    },
    {
      "author": "Tessa Flores",
      "content": "It may only be the final days of October, but its already time to be thinking about one of the holidays most fun gifting traditions: Advent calendars, a delightful concept that offers a daily surpris\u2026 [+1644 chars]",
      "description": "Start your holiday gifting now with these calendars featuring La Mer skin care, Diptyque candles, wine bottles and more.",
      "publishedAt": "2023-10-24T09:45:26Z",
      "source": {
        "id": "the-huffington-post",
        "name": "The Huffington Post"
      },
      "title": "The 2023 Advent Calendars To Buy Immediately Before They Sell Out",
      "url": "https://www.huffpost.com/entry/best-advent-calendars-2023_l_653001d0e4b03b213b08437a",
      "urlToImage": "https://img.huffingtonpost.com/asset/65305143230000aa0054a973.jpg?ops=1200_630"
    },
    {
      "author": "Julia Ries",
      "content": "Pickleball is accessible, affordable and also good for your physical and mental health.\r\nBy now, youve probably seen a headline or two (or 200) labeling pickleball the fastest-growing sport in the co\u2026 [+6182 chars]",
      "description": "A new study reveals that the popular sport may be more than just a fun workout.",
      "publishedAt": "2023-10-24T09:45:26Z",
      "source": {
        "id": "the-huffington-post",
        "name": "The Huffington Post"
      },
      "title": "The 1 Unexpected Health Benefit Of Playing Pickleball",
      "url": "https://www.huffpost.com/entry/pickleball-mental-health-benefit_l_6536af5ee4b011a9cf7a97ba",
      "urlToImage": "https://img.huffingtonpost.com/asset/6536dba3230000c10c54ad35.jpeg?ops=1200_630"
    },
    {
      "author": "Griffin Wynne",
      "content": "HuffPost and its publishing partners may receive a commission from some purchases made via links on this page. Every item is independently curated by the HuffPost Shopping team. Prices and availabili\u2026 [+5094 chars]",
      "description": "This $7 rug tape is the grippy savior you\u2019ve been waiting for.",
      "publishedAt": "2023-10-24T09:45:26Z",
      "source": {
        "id": "the-huffington-post",
        "name": "The Huffington Post"
      },
      "title": "The $7 Hack That Made My Handmade Rug Look Perfect",
      "url": "https://www.huffpost.com/entry/no-slip-rug-tape_l_652d4e92e4b03b213b06ba95",
      "urlToImage": "https://img.huffingtonpost.com/asset/653145ad1f00002b071bad9d.png?ops=1200_630"
    },
    {
      "author": "BuzzFeed Shopping",
      "content": "I have the Ellie Nap Dress in two styles (navy poplin and botanical garden crepe) and absolutely adore them. I feel super comfortable in them and, honestly, like a princess! I get tons of compliments\u2026 [+678 chars]",
      "description": "Give your wardrobe a refresh with these super-soft cardigans, adorable dresses and comfy pants.",
      "publishedAt": "2023-10-24T09:45:26Z",
      "source": {
        "id": "the-huffington-post",
        "name": "The Huffington Post"
      },
      "title": "Just 37 Pieces Of Clothing Your Closet Would Be Thrilled To Meet",
      "url": "https://www.huffpost.com/entry/stylish-clothing-upgrade-closet_l_65302d61e4b00565b6229dc1",
      "urlToImage": "https://img.huffingtonpost.com/asset/653448a81f000086001baf3a.jpg?ops=1200_630"
    },
    {
      "author": "AP",
      "content": "WASHINGTON (AP) The Pentagon has sent military advisers, including a Marine Corps general versed in urban warfare, to Israel to aid in its war planning and is speeding multiple sophisticated air defe\u2026 [+5009 chars]",
      "description": "The Pentagon has sent advisers, including a Marine Corps general versed in urban warfare, to Israel to assist in its plans to conduct a ground assault in Gaza.",
      "publishedAt": "2023-10-24T03:51:12Z",
      "source": {
        "id": "the-huffington-post",
        "name": "The Huffington Post"
      },
      "title": "Pentagon Rushes Defenses And Advisers To Middle East As Israel's Ground Assault In Gaza Looms",
      "url": "https://www.huffpost.com/entry/pentagon-advisers-defenses-middle-east-israel_n_65373e68e4b011a9cf7ac651",
      "urlToImage": "https://img.huffingtonpost.com/asset/65373e691f00002c071bb0df.jpeg?ops=1200_630"
    },
    {
      "author": "AP",
      "content": "THOMASTON, Ga. (AP) A Georgia man has been charged with murder after police said he killed his girlfriend, stuffed her body in a suitcase and stashed it in the closet of the apartment they shared.\r\nF\u2026 [+1123 chars]",
      "description": "Freddrick Durham allegedly stuffed Margret Dubignon\u2019s body into the suitcase before putting it into a closet.",
      "publishedAt": "2023-10-23T23:57:10Z",
      "source": {
        "id": "the-huffington-post",
        "name": "The Huffington Post"
      },
      "title": "Georgia Man Charged With Murder After Girlfriend's Body Found In Suitcase",
      "url": "https://www.huffpost.com/entry/ap-us-body-in-suitcase-georgia_n_65370696e4b0c85561024b62",
      "urlToImage": "https://img.huffingtonpost.com/asset/6537071f1f00002c071bb0d0.jpeg?ops=1200_630"
    },
    {
      "author": "AP",
      "content": "FORT LAUDERDALE, Fla. (AP) A California property manager was sentenced to a year in federal prison for sending more than 200 vile online messages to a father of a teenage girl who died in the 2018 ma\u2026 [+2022 chars]",
      "description": "A California business owner will spend a year in federal prison for sending more than 200 vile online messages to a father whose daughter was killed in a Florida school massacre.",
      "publishedAt": "2023-10-23T23:48:48Z",
      "source": {
        "id": "the-huffington-post",
        "name": "The Huffington Post"
      },
      "title": "Prison Time For California Man Who Sent Vile Messages To Gun Massacre Victim's Dad",
      "url": "https://www.huffpost.com/entry/bc-us-school-shooting-florida-cyberstalker_n_653704d5e4b011a9cf7abf92",
      "urlToImage": "https://img.huffingtonpost.com/asset/653704d8230000870028871d.jpeg?ops=1200_630"
    }
  ],
  "status": "ok",
  "totalResults": 10
}