{
  "articles": [
    {
      "author": "BBC News",
      "description": "National Counterterrorism Center Director Joe Kent says  Trump \"started this war due to pressure from Israel\" and its powerful American lobby.",
      "publishedAt": null,
      "title": "Top US counterterrorism official resigns over Iran war",
      "url": "https://www.bbc.co.uk/news/articles/cg4g66r3z40o",
      "urlToImage": "https://ichef.bbci.co.uk/ace/branded_news/1200/cpsprodpb/1a2d/live/537ff930-6139-11ee-b101-6f93d6dfbcc2.png"
    },
    {
      "author": "BBC News",
      "description": "The Radio 1 Breakfast host was joined by a special guest on the latest leg of his charity challenge.",
      "publishedAt": null,
      "title": "Prince William joins Greg James on Comic Relief bike ride",
      "url": "https://www.bbc.co.uk/news/articles/c3rzgg8wp52o",
      "urlToImage": "https://ichef.bbci.co.uk/ace/branded_news/1200/cpsprodpb/a492/live/02262e30-220a-11f1-9c8b-79913dd99d21.jpg"
    },
    {
      "author": "BBC News",
      "description": "The star has spoken about the viral images that appeared to show her marrying partner Tom Holland.",
      "publishedAt": null,
      "title": "Zendaya: 'Many people fooled' by AI wedding pics",
      "url": "https://www.bbc.co.uk/news/articles/clyz7llp4k2o",
      "urlToImage": "https://ichef.bbci.co.uk/ace/branded_news/1200/cpsprodpb/cc9b/live/1d5485b0-2207-11f1-9c8b-79913dd99d21.png"
    },
    {
      "author": "BBC News",
      "description": "Only learners will be able to book a car driving test under new rules to make the system fairer.",
      "publishedAt": null,
      "title": "Dates confirmed for new driving test booking rules",
      "url": "https://www.bbc.co.uk/news/articles/c79522r09qqo",
      "urlToImage": "https://ichef.bbci.co.uk/ace/branded_news/1200/cpsprodpb/ef23/live/a5eaed10-9332-11f0-95b6-f751ff87aca7.jpg"
    },
    {
      "author": "BBC News",
      "description": "Lenders have hiked rates on new deals and withdrawn products as war creates uncertainty in the markets.",
      "publishedAt": null,
      "title": "New mortgage costs soar \u00a3788 a year in two weeks",
      "url": "https://www.bbc.co.uk/news/articles/c0mgd3z1e9ko",
      "urlToImage": "https://ichef.bbci.co.uk/ace/branded_news/1200/cpsprodpb/fc6f/live/80869600-21e4-11f1-a42b-a3f1101f2a6d.jpg"
    },
    {
      "author": "BBC News",
      "description": "Downing Street says the agreement bring together \"Ukrainian expertise and the UK's industrial base\".",
      "publishedAt": null,
      "title": "Zelensky to visit Starmer to sign new Ukraine-UK defence pact",
      "url": "https://www.bbc.co.uk/news/articles/c15xeyny73wo",
      "urlToImage": "https://ichef.bbci.co.uk/ace/branded_news/1200/cpsprodpb/5fdd/live/8e094650-21d1-11f1-af4a-cf8a1aeceb1e.jpg"
    },
    {
      "author": "BBC News",
      "description": "Gemma Ahern was three when her dad killed her mum - and at six she had to live with him again.",
      "publishedAt": null,
      "title": "Jade's Law: I had to live with my dad after he killed my mum",
      "url": "https://www.bbc.co.uk/news/articles/cvg3e70pnpeo",
      "urlToImage": "https://ichef.bbci.co.uk/ace/branded_news/1200/cpsprodpb/c88b/live/dcbca130-2117-11f1-ac51-03f49875b3d3.jpg"
    },
    {
      "author": "BBC News",
      "description": "Alanah Thomspon French says her application was not progressed as her car was more than 10 years old.",
      "publishedAt": null,
      "title": "Woman, 18, not shortlisted for job at estate agents as 'car is too old'",
      "url": "https://www.bbc.co.uk/news/articles/c4g7yd202ngo",
      "urlToImage": "https://ichef.bbci.co.uk/ace/branded_news/1200/cpsprodpb/8d9d/live/542b32f0-1d5c-11f1-a5ee-870cbdcb0f98.jpg"
    },
    {
      "author": "BBC News",
      "description": "The Chancellor has set out the government's plan for economic growth, which also includes closer ties to the EU.",
      "publishedAt": null,
      "title": "Mayors to gain more spending power under Reeves tax plans",
      "url": "https://www.bbc.co.uk/news/articles/c0k16zdr1r1o",
      "urlToImage": "https://ichef.bbci.co.uk/ace/branded_news/1200/cpsprodpb/67c2/live/6f775d60-2214-11f1-a79a-77e93010d956.jpg"
    },
    {
      "author": "BBC News",
      "description": "Rhonda Montgomery was scammed out of \u00a317,000 by fraudsters pretending to work for Revolut.",
      "publishedAt": null,
      "title": "Impersonation Fraud: Woman scammed out of \u00a317k travelled across UK to try to find them",
      "url": "https://www.bbc.co.uk/news/articles/c1kgx0xppzeo",
      "urlToImage": "https://ichef.bbci.co.uk/ace/branded_news/1200/cpsprodpb/a059/live/f01c1550-1ecc-11f1-84c5-132fa5d854db.jpg"
    }
  ],
  "sortBy": "top",
  "source": "bbc-news",
  "status": "ok"
}