{
  "articles": [
    {
      "author": "BBC News",
      "description": "Wingstop, Burger King, and others have walked away from an industry commitment to avoid using fast-growing chickens",
      "publishedAt": null,
      "title": "KFC, Nando's, and others ditch chicken welfare pledge as demand soars",
      "url": "https://www.bbc.co.uk/news/articles/cm2r6jqm042o",
      "urlToImage": "https://ichef.bbci.co.uk/ace/branded_news/1200/cpsprodpb/ad8a/live/7f74d6e0-0e67-11f1-9f23-b3f349b149c7.jpg"
    },
    {
      "author": "BBC News",
      "description": "After the former prince's arrest, Reuters photographer Phil Noble began a six-hour drive to Norfolk.",
      "publishedAt": null,
      "title": "A tip-off and 'more luck than judgement': The story behind Andrew car snap",
      "url": "https://www.bbc.co.uk/news/articles/c93wl4kp671o",
      "urlToImage": "https://ichef.bbci.co.uk/ace/branded_news/1200/cpsprodpb/d16f/live/74fdad20-0e5f-11f1-bbc2-b7e92c82a79f.jpg"
    },
    {
      "author": "BBC News",
      "description": "Kamran Aman was subjected to further racist abuse as he lay dying on the floor of a neighbour's house.",
      "publishedAt": null,
      "title": "Barry teens sentenced for racist murder of stranger delivering food to his mum",
      "url": "https://www.bbc.co.uk/news/articles/c8r1kmz614po",
      "urlToImage": "https://ichef.bbci.co.uk/ace/branded_news/1200/cpsprodpb/c7a3/live/4caa5f40-0c10-11f1-ad4b-755d3b02c9a5.jpg"
    },
    {
      "author": "BBC News",
      "description": "Nasa sets the launch date following a successful \"wet dress rehearsal\" of the Artemis II mission.",
      "publishedAt": null,
      "title": "Nasa targets March 6 date to send humans back around the Moon",
      "url": "https://www.bbc.co.uk/news/articles/c86y1g6wde3o",
      "urlToImage": "https://ichef.bbci.co.uk/ace/branded_news/1200/cpsprodpb/d945/live/86f4ff70-08d7-11f1-9972-d3f265c101c6.jpg"
    },
    {
      "author": "BBC News",
      "description": "The defendants cannot be named for legal reasons at this stage.",
      "publishedAt": null,
      "title": "Man charged with raping unconscious wife with other men for years",
      "url": "https://www.bbc.co.uk/news/articles/cqxde27ep5qo",
      "urlToImage": "https://ichef.bbci.co.uk/ace/branded_news/1200/cpsprodpb/3f1a/live/dcd53690-0e71-11f1-9acc-6bf6c7adf476.jpg"
    },
    {
      "author": "BBC News",
      "description": "The Supreme Court has weakened Trump's hand in dealing with other nations, writes Anthony Zurcher.",
      "publishedAt": null,
      "title": "Tariffs ruling is major blow to Trump's second-term agenda",
      "url": "https://www.bbc.co.uk/news/articles/cx2jqgdn719o",
      "urlToImage": "https://ichef.bbci.co.uk/ace/branded_news/1200/cpsprodpb/f90b/live/b382ce60-0e76-11f1-9acc-6bf6c7adf476.jpg"
    },
    {
      "author": "BBC News",
      "description": "Family face a nine month battle with insurance giant Zurich which has now apologised.",
      "publishedAt": null,
      "title": "South west couple left with $200k bill after baby born in US",
      "url": "https://www.bbc.co.uk/news/articles/cx2r7d4gzz1o",
      "urlToImage": "https://ichef.bbci.co.uk/ace/branded_news/1200/cpsprodpb/3b99/live/9e66a8a0-0dac-11f1-9fe5-57999fe11004.jpg"
    },
    {
      "author": "BBC News",
      "description": "The old friends come face-to-face with a new threat - a frog-like tablet device called Lilypad.",
      "publishedAt": null,
      "title": "Toy Story 5: Woody and Buzz reunited in first look at new Disney movie",
      "url": "https://www.bbc.co.uk/news/articles/c98q9g68vyno",
      "urlToImage": "https://ichef.bbci.co.uk/ace/branded_news/1200/cpsprodpb/7bb8/live/3d2f22d0-0e5e-11f1-8446-9d45fce2423a.jpg"
    },
    {
      "author": "BBC News",
      "description": "From being arrested at home to detention in a cell, this is how the former prince's detention unfolded.",
      "publishedAt": null,
      "title": "How Andrew's 11-hour detention on his birthday played out",
      "url": "https://www.bbc.co.uk/news/articles/cz9qy5057e0o",
      "urlToImage": "https://ichef.bbci.co.uk/ace/branded_news/1200/cpsprodpb/564c/live/809f6570-0e6d-11f1-a7d2-13765adb9f56.jpg"
    },
    {
      "author": "BBC News",
      "description": "John McAllister managed to avoid forking out for a hotel during his bargain 24-hour trip to Milan.",
      "publishedAt": null,
      "title": "Winter Olympics trip 'cost same as seeing Barry Town in Llandudno'",
      "url": "https://www.bbc.co.uk/news/articles/cn8zv0lpvvwo",
      "urlToImage": "https://ichef.bbci.co.uk/ace/branded_news/1200/cpsprodpb/6499/live/16b34df0-0dd9-11f1-8aca-8d545890fa70.jpg"
    }
  ],
  "sortBy": "top",
  "source": "bbc-news",
  "status": "ok"
}