{
  "articles": [
    {
      "author": "BBC News",
      "description": "The Republican becomes only the sixth elected member of the lower chamber of Congress ever to be removed.",
      "publishedAt": null,
      "title": "US House votes to expel George Santos from Congress",
      "url": "http://www.bbc.co.uk/news/world-us-canada-67593885",
      "urlToImage": "https://ichef.bbci.co.uk/news/1024/branded_news/433A/production/_131901271_gettyimages-1824779422-1.jpg"
    },
    {
      "author": "BBC News",
      "description": "More than 100 hostages have been freed from Gaza under the week-long temporary ceasefire - but it's due to expire shortly.",
      "publishedAt": null,
      "title": "Israel-Gaza war: More hostages freed but temporary truce about to expire",
      "url": "http://www.bbc.co.uk/news/live/world-middle-east-67584895",
      "urlToImage": "https://m.files.bbci.co.uk/modules/bbc-morph-news-waf-page-meta/5.3.0/bbc_news_logo.png"
    },
    {
      "author": "BBC News",
      "description": "Sandra Day O'Connor, the first woman to sit on the US Supreme Court, has died aged 93",
      "publishedAt": null,
      "title": "Ex-Supreme Court Justice Sandra Day O'Connor dies aged 93",
      "url": "http://www.bbc.co.uk/news/world-us-canada-67593879",
      "urlToImage": "https://ichef.bbci.co.uk/news/1024/branded_news/83B3/production/_115651733_breaking-large-promo-nc.png"
    },
    {
      "author": "BBC News",
      "description": "Ukraine's president meets frontline commanders and says winter is a new phase of the war with Russia.",
      "publishedAt": null,
      "title": "Ukraine war: Zelensky says fortifying front lines must be accelerated",
      "url": "http://www.bbc.co.uk/news/world-europe-67587331",
      "urlToImage": "https://ichef.bbci.co.uk/news/1024/branded_news/3A01/production/_131894841_6adfe195c614392a35b59302768279be708fb03e0_29_2500_14071000x563.jpg"
    },
    {
      "author": "BBC News",
      "description": "The state's governor, Ron DeSantis, says party chairman Christian Ziegler should resign.",
      "publishedAt": null,
      "title": "Top Florida Republican official faces sexual assault investigation",
      "url": "http://www.bbc.co.uk/news/world-us-canada-67560516",
      "urlToImage": "https://ichef.bbci.co.uk/news/1024/branded_news/171A0/production/_131842649_gettyimages-1813811801.jpg"
    },
    {
      "author": "BBC News",
      "description": "The US unveils rules aimed at keeping Chinese components out of electric cars sold in the country.",
      "publishedAt": null,
      "title": "US aims to limit China's role in electric cars",
      "url": "http://www.bbc.co.uk/news/business-67593199",
      "urlToImage": "https://ichef.bbci.co.uk/news/1024/branded_news/BF04/production/_131900984_67594497.jpg"
    },
    {
      "author": "BBC News",
      "description": "World leaders agree to tackle the huge carbon footprint of the food we produce and eat.",
      "publishedAt": null,
      "title": "COP28: UN climate talks take aim at planet-warming food",
      "url": "http://www.bbc.co.uk/news/science-environment-67594303",
      "urlToImage": "https://ichef.bbci.co.uk/news/1024/branded_news/33AE/production/_131903231_whatsappimage2023-12-01at11.08.53.jpg"
    },
    {
      "author": "BBC News",
      "description": "Tree Paine has been part of the singer's team since 2014, calling the Deuxmoi rumours \"fabricated lies\".",
      "publishedAt": null,
      "title": "Taylor Swift: Publicist denies star secretly married Joe Alwyn",
      "url": "http://www.bbc.co.uk/news/newsbeat-67588850",
      "urlToImage": "https://ichef.bbci.co.uk/news/1024/branded_news/3364/production/_131865131_gettyimages-1189844075.jpg"
    },
    {
      "author": "BBC News",
      "description": "After the naming of names in the race row, the Royal Family has to tackle difficult questions.",
      "publishedAt": null,
      "title": "How the Palace got stuck in Scobie-gate",
      "url": "http://www.bbc.co.uk/news/uk-67589069",
      "urlToImage": "https://ichef.bbci.co.uk/news/1024/branded_news/16F02/production/_131845939_omid_scobie.jpg"
    },
    {
      "author": "BBC Sport",
      "description": "Buffalo Bills linebacker Von Miller turns himself in to police to face a charge of assaulting a pregnant woman.",
      "publishedAt": null,
      "title": "Miller turns himself in to police after arrest warrant",
      "url": "http://www.bbc.co.uk/sport/american-football/67584335",
      "urlToImage": "https://ichef.bbci.co.uk/live-experience/cps/624/cpsprodpb/C561/production/_131892505_gettyimages-1765168806-1.jpg"
    }
  ],
  "sortBy": "top",
  "source": "bbc-news",
  "status": "ok"
}