{
  "articles": [
    {
      "author": "BBC News",
      "description": "On 24 March he ended his programme saying \"back tomorrow\" and the following morning Gary Davies was standing in for him.",
      "publishedAt": null,
      "title": "Scott Mills sacked from BBC Radio 2 over 'personal conduct'",
      "url": "https://www.bbc.co.uk/news/articles/ckge1yn50y8o",
      "urlToImage": "https://ichef.bbci.co.uk/ace/branded_news/1200/cpsprodpb/fe86/live/a6881980-2c27-11f1-a79a-77e93010d956.jpg"
    },
    {
      "author": "BBC News",
      "description": "They are understood to have made \"alternative plans\" instead of joining the Royal Family in Windsor.",
      "publishedAt": null,
      "title": "Princesses Beatrice and Eugenie will not attend Easter church service",
      "url": "https://www.bbc.co.uk/news/articles/cx247087ejko",
      "urlToImage": "https://ichef.bbci.co.uk/ace/branded_news/1200/cpsprodpb/bea4/live/cf19dae0-2c50-11f1-824a-573867676f63.jpg"
    },
    {
      "author": "BBC News",
      "description": "Radio 2 DJ Scott Mills was sacked from the BBC on Monday following allegations over his conduct.",
      "publishedAt": null,
      "title": "Scott Mills' abrupt sacking creates another headache for the BBC",
      "url": "https://www.bbc.co.uk/news/articles/clyr1z4kre0o",
      "urlToImage": "https://ichef.bbci.co.uk/ace/branded_news/1200/cpsprodpb/aefc/live/d94ea670-2c42-11f1-86ea-7b38ea33820f.jpg"
    },
    {
      "author": "BBC News",
      "description": "The star was diagnosed with a rare condition that affects her singing voice and her ability to walk.",
      "publishedAt": null,
      "title": "Celine Dion announces comeback shows four years after Stiff Person Syndrome diagnosis",
      "url": "https://www.bbc.co.uk/news/articles/c0708dkm2lko",
      "urlToImage": "https://ichef.bbci.co.uk/ace/branded_news/1200/cpsprodpb/1775/live/f8b3a060-2c0b-11f1-b5a6-011ae525765c.jpg"
    },
    {
      "author": "BBC News",
      "description": "While both crises involve oil, experts say there are some important differences between what happened in the 1970s and today.",
      "publishedAt": null,
      "title": "What was the 1970s oil crisis, and are we heading for something worse?",
      "url": "https://www.bbc.co.uk/news/articles/c78lj4976lvo",
      "urlToImage": "https://ichef.bbci.co.uk/ace/branded_news/1200/cpsprodpb/e9e7/live/befaf650-2c2b-11f1-b8c9-f5058c0aec9a.jpg"
    },
    {
      "author": "BBC News",
      "description": "The City regulator says 12.1 million motor finance deals will be eligible for redress.",
      "publishedAt": null,
      "title": "Millions of drivers mis-sold car finance to receive average \u00a3829 in compensation",
      "url": "https://www.bbc.co.uk/news/articles/c9vlm2ggrwlo",
      "urlToImage": "https://ichef.bbci.co.uk/ace/branded_news/1200/cpsprodpb/09ba/live/d4f128a0-29e5-11f1-81d4-f1e3c77fafb4.jpg"
    },
    {
      "author": "BBC News",
      "description": "Fans, who paid up to $450 (\u00a3340), complained of a grey convention centre backdrop and a \"swag bag\" that included only a plastic pouch with a Barbie hand sanitiser.",
      "publishedAt": null,
      "title": "Barbie Dream Fest in Florida to issue refunds after fan complaints",
      "url": "https://www.bbc.co.uk/news/articles/cp3l1422d3qo",
      "urlToImage": "https://ichef.bbci.co.uk/ace/branded_news/1200/cpsprodpb/e31d/live/7e4cf670-2c68-11f1-934f-036468834728.jpg"
    },
    {
      "author": "BBC News",
      "description": "The Australian town has been in the spotlight since Dezi Freeman shot dead two police officers last year.",
      "publishedAt": null,
      "title": "Dezi Freeman: Porepunkah residents on hopes after manhunt ends",
      "url": "https://www.bbc.co.uk/news/articles/cq59wj31vl4o",
      "urlToImage": "https://ichef.bbci.co.uk/ace/branded_news/1200/cpsprodpb/f1ed/live/a1fee4e0-2c48-11f1-b979-37139b7cb8c6.jpg"
    },
    {
      "author": "BBC News",
      "description": "The new law, passed on Monday, was pushed hard by the far-right and Security Minister Itamar Ben-Gvir.",
      "publishedAt": null,
      "title": "Palestinians convicted of deadly attacks face death penalty under new Israeli law",
      "url": "https://www.bbc.co.uk/news/articles/cp8dkd6lnjdo",
      "urlToImage": "https://ichef.bbci.co.uk/ace/branded_news/1200/cpsprodpb/4290/live/72065650-2c80-11f1-b297-95b0a0a8331e.jpg"
    },
    {
      "author": "BBC News",
      "description": "Anne Marie Boyle suffered a brain injury and subsequent seizures which led to her losing her business, her ability to drive and her confidence.",
      "publishedAt": null,
      "title": "I turned down MMA fighter on a night out - so he punched me",
      "url": "https://www.bbc.co.uk/news/articles/c86e3dpj2d9o",
      "urlToImage": "https://ichef.bbci.co.uk/ace/branded_news/1200/cpsprodpb/e55d/live/c6dd6310-29d0-11f1-9958-b14c758dcc6e.jpg"
    }
  ],
  "sortBy": "top",
  "source": "bbc-news",
  "status": "ok"
}