{
  "articles": [
    {
      "author": "BBC News",
      "description": "US media reports the suspect in a shooting that killed 18 people has been found dead.",
      "publishedAt": null,
      "title": "Maine mass shooting suspect found dead - reports",
      "url": "http://www.bbc.co.uk/news/world-us-canada-67247726",
      "urlToImage": "https://ichef.bbci.co.uk/news/1024/branded_news/167DC/production/_131542129_c0889d86a4d6e4a5bd19891f89daad179af875090_390_5768_32441000x563.jpg"
    },
    {
      "author": "BBC News",
      "description": "After a shooting in his hometown, Jared Golden seeks \"forgiveness\" for his past opposition to gun control.",
      "publishedAt": null,
      "title": "Maine shootings: Democrat reverses course on assault weapons ban",
      "url": "http://www.bbc.co.uk/news/world-us-canada-67240152",
      "urlToImage": "https://ichef.bbci.co.uk/news/1024/branded_news/120EC/production/_131546937_gettyimages-1351340216-1.jpg"
    },
    {
      "author": "BBC News",
      "description": "The US fashion brand is jointly accused with its ex-CEO of participating in a sex-trafficking venture.",
      "publishedAt": null,
      "title": "Lawsuit accuses Abercrombie & Fitch of funding sex-trafficking operation",
      "url": "http://www.bbc.co.uk/news/world-us-canada-67238812",
      "urlToImage": "https://ichef.bbci.co.uk/news/1024/branded_news/510E/production/_131305702_abercrombie_index_jeffries_976-2.png"
    },
    {
      "author": "BBC News",
      "description": "Authorities deny that Armita Geravand fell into a coma after being assaulted by morality police.",
      "publishedAt": null,
      "title": "Armita Geravand: Iranian girl who collapsed on Tehran metro dies",
      "url": "http://www.bbc.co.uk/news/world-middle-east-67248449",
      "urlToImage": "https://ichef.bbci.co.uk/news/1024/branded_news/25D2/production/_131328690_mediaitem131328689.jpg"
    },
    {
      "author": "BBC News",
      "description": "At least 21 people have died after a fire broke out at an ArcelorMittal-owned mine in Kazakhstan",
      "publishedAt": null,
      "title": "Kazakhstan mine fire leaves at least 21 dead",
      "url": "http://www.bbc.co.uk/news/world-europe-67248267",
      "urlToImage": "https://ichef.bbci.co.uk/news/1024/branded_news/861F/production/_131553343_090810721f145a0311bd22f240977ed8fc87a22a0_0_5517_37521000x680.jpg"
    },
    {
      "author": "BBC News",
      "description": "Ivanka Trump will have to testify in business fraud case against her father and brothers, a New York judge rules",
      "publishedAt": null,
      "title": "Ivanka Trump must testify in fraud case, judge rules",
      "url": "http://www.bbc.co.uk/news/world-us-canada-67243100",
      "urlToImage": "https://ichef.bbci.co.uk/news/1024/branded_news/83B3/production/_115651733_breaking-large-promo-nc.png"
    },
    {
      "author": "BBC News",
      "description": "A new investigation by Canadian broadcaster CBC has questioned her claims of indigenous ancestry.",
      "publishedAt": null,
      "title": "Doubt cast on indigenous roots of Buffy Sainte-Marie",
      "url": "http://www.bbc.co.uk/news/world-us-canada-67242752",
      "urlToImage": "https://ichef.bbci.co.uk/news/1024/branded_news/0D38/production/_131548330_gettyimages-612063860.jpg"
    },
    {
      "author": "BBC News",
      "description": "They say their routes from Pakistan are \u201csafe\u201d, with one claiming \u201chundreds\u201d are transported daily.",
      "publishedAt": null,
      "title": "Going undercover to reveal people smugglers' sales tactics",
      "url": "http://www.bbc.co.uk/news/world-asia-66984050",
      "urlToImage": "https://ichef.bbci.co.uk/news/1024/branded_news/115E7/production/_131534117_gettyimages-1204298375.jpg"
    },
    {
      "author": "BBC News",
      "description": "Antisemitic and Islamophobic hate crimes recorded by Met Police have risen dramatically since 7 October.",
      "publishedAt": null,
      "title": "Gaza war: Hate crime soars in London during conflict",
      "url": "http://www.bbc.co.uk/news/uk-67241374",
      "urlToImage": "https://ichef.bbci.co.uk/news/1024/branded_news/1716E/production/_131547549_cded3b40ee7207b4031bcc7e42d6d0558a6592c80_0_5500_36671000x667.jpg"
    },
    {
      "author": "BBC News",
      "description": "Video shows the Chinese jet flying within 10ft (3m) of its B-52 bomber, according to US military officials.",
      "publishedAt": null,
      "title": "US says a Chinese plane caused danger of collision",
      "url": "http://www.bbc.co.uk/news/world-us-canada-67210528",
      "urlToImage": "https://ichef.bbci.co.uk/news/1024/branded_news/9E43/production/_131551504_p0gp92qn.jpg"
    }
  ],
  "sortBy": "top",
  "source": "bbc-news",
  "status": "ok"
}