{
  "articles": [
    {
      "author": "BBC News",
      "description": "Interior Minister G\u00e9rald Darmanin said passers-by were targeted in the Quai de Grenelle area.",
      "publishedAt": null,
      "title": "Central Paris attack leaves one dead and one injured",
      "url": "http://www.bbc.co.uk/news/world-europe-67604591",
      "urlToImage": "https://ichef.bbci.co.uk/news/1024/branded_news/83B3/production/_115651733_breaking-large-promo-nc.png"
    },
    {
      "author": "BBC News",
      "description": "Israel shifts its focus southwards, as the US vice president warns of \u201cdevastating\u201d human suffering.",
      "publishedAt": null,
      "title": "Israel-Gaza live news: Israel continues bombing of south Gaza as US urges protection of civilians",
      "url": "http://www.bbc.co.uk/news/live/world-middle-east-67605703",
      "urlToImage": "https://m.files.bbci.co.uk/modules/bbc-morph-news-waf-page-meta/5.3.0/bbc_news_logo.png"
    },
    {
      "author": "BBC News",
      "description": "Henry Kissinger died aged 100 this week. His policies caused widespread destruction in Cambodia.",
      "publishedAt": null,
      "title": "Henry Kissinger's Cambodia legacy of bombs and chaos",
      "url": "http://www.bbc.co.uk/news/world-asia-67582813",
      "urlToImage": "https://ichef.bbci.co.uk/news/1024/branded_news/C922/production/_131909415_mediaitem131890772.jpg"
    },
    {
      "author": "BBC News",
      "description": "Musk's profane attack on advertisers baffled experts - without adverts, how would X survive?",
      "publishedAt": null,
      "title": "Could X go bankrupt under Elon Musk?",
      "url": "http://www.bbc.co.uk/news/technology-67599937",
      "urlToImage": "https://ichef.bbci.co.uk/news/1024/branded_news/F780/production/_131906336_gettyimages-1821095235.jpg"
    },
    {
      "author": "BBC News",
      "description": "Nine people are also injured during a Catholic service at a university in Mindanao.",
      "publishedAt": null,
      "title": "Mindanao: Three killed in explosion at Catholic Mass in Philippines",
      "url": "http://www.bbc.co.uk/news/world-asia-67604592",
      "urlToImage": "https://ichef.bbci.co.uk/news/1024/branded_news/83B3/production/_115651733_breaking-large-promo-nc.png"
    },
    {
      "author": "BBC News",
      "description": "Satirical film American Fiction follows a black writer trying to make the literary world change its ways.",
      "publishedAt": null,
      "title": "American Fiction director says white audiences are too comfortable with black clich\u00e9s",
      "url": "http://www.bbc.co.uk/news/entertainment-arts-67591392",
      "urlToImage": "https://ichef.bbci.co.uk/news/1024/branded_news/7D6E/production/_131901123_a2318aeb-8689-4dc1-a28c-964651aa656d.jpg"
    },
    {
      "author": "BBC News",
      "description": "Shane MacGowan gave voice to an Irish-English generation, writes author Joseph O'Connor.",
      "publishedAt": null,
      "title": "Shane MacGowan: A unifying Irish-English voice, in time of bombs and bullets",
      "url": "http://www.bbc.co.uk/news/entertainment-arts-67581647",
      "urlToImage": "https://ichef.bbci.co.uk/news/1024/branded_news/150CB/production/_131891268_mcgowan.png"
    },
    {
      "author": "BBC News",
      "description": "The BJP is poised to win in three states, while Congress is ahead in the southern state of Telangana.",
      "publishedAt": null,
      "title": "State poll results: Key wins boost Indian PM Modi's re-election bid",
      "url": "http://www.bbc.co.uk/news/world-asia-india-67605339",
      "urlToImage": "https://ichef.bbci.co.uk/news/1024/branded_news/16B3E/production/_131909929_gettyimages-1768334265-594x594.jpg"
    },
    {
      "author": "BBC News",
      "description": "The coast guard said the growing numbers of Chinese military boats in the area was \"alarming\".",
      "publishedAt": null,
      "title": "Philippines accuses China of swarming reef in South China Sea",
      "url": "http://www.bbc.co.uk/news/world-asia-67605630",
      "urlToImage": "https://ichef.bbci.co.uk/news/1024/branded_news/15E65/production/_131910798_82b28739cc52ccc4090d75d2474e2406918fec03.jpg"
    },
    {
      "author": "BBC News",
      "description": "The referendum asks if Venezuelans support the claim to two thirds of the land controlled by Guyana.",
      "publishedAt": null,
      "title": "Essequibo: Venezuela votes on claim to Guyana-controlled oil region",
      "url": "http://www.bbc.co.uk/news/world-latin-america-67583582",
      "urlToImage": "https://ichef.bbci.co.uk/news/1024/branded_news/6086/production/_131901742_gettyimages-1808074564.jpg"
    }
  ],
  "sortBy": "top",
  "source": "bbc-news",
  "status": "ok"
}