{
  "articles": [
    {
      "author": "BBC News",
      "description": "Blaise Metreweli \"neither knew nor met\" her grandfather, reportedly a chief Nazi informant during World War Two.",
      "publishedAt": null,
      "title": "Blaise Metreweli: MI6 distances new chief from Nazi grandfather",
      "url": "https://www.bbc.co.uk/news/articles/c0l406gpydgo",
      "urlToImage": "https://ichef.bbci.co.uk/ace/branded_news/1200/cpsprodpb/38c9/live/f1c75230-5356-11f0-b4be-8f7caf53b80c.jpg"
    },
    {
      "author": "BBC News",
      "description": "Trasi and her husband originally planned to have a ceremony next year, but had to bring it forward.",
      "publishedAt": null,
      "title": "Terminally ill Caerphilly woman renew vows after donated wedding",
      "url": "https://www.bbc.co.uk/news/articles/crmvjpdgx20o",
      "urlToImage": "https://ichef.bbci.co.uk/ace/branded_news/1200/cpsprodpb/47ab/live/ff2272c0-5342-11f0-bf89-7dc3da709f40.jpg"
    },
    {
      "author": "BBC News",
      "description": "The UK could see its hottest day of the year on Monday, as a likely heatwave coincides with Glastonbury and Wimbledon.",
      "publishedAt": null,
      "title": "UK weather: Health alerts come into force ahead of second heatwave",
      "url": "https://www.bbc.co.uk/news/articles/cy4y8exrw0zo",
      "urlToImage": "https://ichef.bbci.co.uk/ace/branded_news/1200/cpsprodpb/6029/live/07236200-536f-11f0-a2ff-17a82c2e8bc4.jpg"
    },
    {
      "author": "BBC News",
      "description": "The UK's biggest festival kicks off this week. Here's who's playing, and a guide to the secret sets.",
      "publishedAt": null,
      "title": "Glastonbury 2025: Full line-up, stage times and secret sets",
      "url": "https://www.bbc.co.uk/news/articles/cx2jd8e6918o",
      "urlToImage": "https://ichef.bbci.co.uk/ace/branded_news/1200/cpsprodpb/5261/live/70766040-409b-11f0-b6e6-4ddb91039da1.jpg"
    },
    {
      "author": "BBC News",
      "description": "The prime minister has made concessions on his welfare bill after an angry response from 120 of his own MPs.",
      "publishedAt": null,
      "title": "We've got the right balance says Keir Starmer, after benefits U-turn",
      "url": "https://www.bbc.co.uk/news/articles/cd78vyl3yvlo",
      "urlToImage": "https://ichef.bbci.co.uk/ace/branded_news/1200/cpsprodpb/f256/live/d6b43c20-535f-11f0-a0b2-13bcfa16c1d6.jpg"
    },
    {
      "author": "BBC News",
      "description": "It handed a significant victory to Donald Trump - and future American presidents.",
      "publishedAt": null,
      "title": "Supreme Court decision on birthright citizenship broadens Trump's power",
      "url": "https://www.bbc.co.uk/news/articles/cj9velv7z4no",
      "urlToImage": "https://ichef.bbci.co.uk/ace/branded_news/1200/cpsprodpb/3192/live/65320840-5367-11f0-a0b2-13bcfa16c1d6.jpg"
    },
    {
      "author": "BBC News",
      "description": "Dame Anna announced this week she was stepping down as editor-in-chief after 37 years.",
      "publishedAt": null,
      "title": "Anna Wintour's legacy and who might replace her as Vogue editor",
      "url": "https://www.bbc.co.uk/news/articles/c3envvyvqydo",
      "urlToImage": "https://ichef.bbci.co.uk/ace/branded_news/1200/cpsprodpb/91df/live/0420aa20-533f-11f0-a2ff-17a82c2e8bc4.jpg"
    },
    {
      "author": "BBC News",
      "description": "Daniel Anjorin's family said in a statement that the schoolboy was kind and had a generous spirit.",
      "publishedAt": null,
      "title": "Man who murdered boy with sword in Hainault jailed for life",
      "url": "https://www.bbc.co.uk/news/articles/cvg977nkl9xo",
      "urlToImage": "https://ichef.bbci.co.uk/ace/branded_news/1200/cpsprodpb/bec4/live/51699560-4dec-11f0-86d5-3b52b53af158.jpg"
    },
    {
      "author": "BBC News",
      "description": "The New Zealand pop star draws a huge crowd for an unannounced appearance on the Woodsies Stage.",
      "publishedAt": null,
      "title": "Lorde kicks off Glastonbury with early surprise set",
      "url": "https://www.bbc.co.uk/news/articles/cdx522wd84zo",
      "urlToImage": "https://ichef.bbci.co.uk/ace/branded_news/1200/cpsprodpb/fe40/live/c5abcf00-5347-11f0-a2ff-17a82c2e8bc4.jpg"
    },
    {
      "author": "BBC News",
      "description": "The singer makes his live return at the festival after releasing a new single.",
      "publishedAt": null,
      "title": "Lewis Capaldi in surprise Glastonbury return after releasing rousing comeback",
      "url": "https://www.bbc.co.uk/news/articles/czdv3y58459o",
      "urlToImage": "https://ichef.bbci.co.uk/ace/branded_news/1200/cpsprodpb/3b38/live/c15808a0-5370-11f0-b4be-8f7caf53b80c.jpg"
    }
  ],
  "sortBy": "top",
  "source": "bbc-news",
  "status": "ok"
}