{
  "articles": [
    {
      "author": "BBC News",
      "description": "The mayor of Jasper said the wildfire  \"ravaged our small, tight-knit mountain community\".",
      "publishedAt": null,
      "title": "'Monster' wildfire may have destroyed up to 50% of town of Jasper",
      "url": "https://www.bbc.co.uk/news/articles/cyj423n2jdgo",
      "urlToImage": "https://ichef.bbci.co.uk/news/1024/branded_news/e0c1/live/87a06720-4abf-11ef-8f0f-0577398c3339.jpg"
    },
    {
      "author": "BBC News",
      "description": "El Mayo co-founded the notorious Sinaloa cartel with El Chapo, who is currently jailed in the US.",
      "publishedAt": null,
      "title": "Ismael 'El Mayo' Zambada: Mexican drug lord arrested in US",
      "url": "https://www.bbc.co.uk/news/articles/c4ng4g31x1wo",
      "urlToImage": "https://ichef.bbci.co.uk/news/1024/branded_news/3d97/live/c6b0baf0-4ae2-11ef-9366-17a663eccfc3.jpg"
    },
    {
      "author": "BBC News",
      "description": "Gaza war expected to be top priority at meeting, a day after the Israeli PM delivered fiery speech to Congress.",
      "publishedAt": null,
      "title": "Benjamin Netanyahu to meet Joe Biden at White House",
      "url": "https://www.bbc.co.uk/news/articles/cg3eppp0n57o",
      "urlToImage": "https://ichef.bbci.co.uk/news/1024/branded_news/416d/live/135cd4b0-4a98-11ef-b7e5-29f47be8e120.jpg"
    },
    {
      "author": "BBC News",
      "description": "Matt Dawson broke his finger only two weeks ago but will join the Kookaburras in their medal campaign.",
      "publishedAt": null,
      "title": "Hockey star Matt Dawson amputates finger to play at Olympics",
      "url": "https://www.bbc.co.uk/news/articles/ckmg7ngkgjeo",
      "urlToImage": "https://ichef.bbci.co.uk/news/1024/branded_news/ef4d/live/59cd64c0-4b04-11ef-8f0f-0577398c3339.jpg"
    },
    {
      "author": "BBC News",
      "description": "The YouTuber's co-host Ava Kris Tyson denies claims online she groomed a teenager when she was 20.",
      "publishedAt": null,
      "title": "MrBeast hires team to investigate Ava Kris Tyson grooming claims",
      "url": "https://www.bbc.co.uk/news/articles/cgr5pgevr39o",
      "urlToImage": "https://ichef.bbci.co.uk/news/1024/branded_news/6ecf/live/c9c71330-4a54-11ef-81b1-e9d694834d0d.jpg"
    },
    {
      "author": "BBC News",
      "description": "New evidence tells us how the gunman's plan came together but not why.",
      "publishedAt": null,
      "title": "Trump shooting: Thomas Crooks' plan and the botched response",
      "url": "https://www.bbc.co.uk/news/articles/cn38px7lyy0o",
      "urlToImage": "https://ichef.bbci.co.uk/news/1024/branded_news/81da/live/9c9bfeb0-4a9b-11ef-b7e5-29f47be8e120.jpg"
    },
    {
      "author": "BBC News",
      "description": "The Friends star has previously spoken about her struggles while trying to have children through IVF.",
      "publishedAt": null,
      "title": "Jennifer Aniston criticises JD Vance's 'childless cat ladies' comment",
      "url": "https://www.bbc.co.uk/news/articles/cpe3pz2pz8no",
      "urlToImage": "https://ichef.bbci.co.uk/news/1024/branded_news/bda4/live/73854920-4a62-11ef-935f-59cf6f181f38.jpg"
    },
    {
      "author": "BBC News",
      "description": "A new study links the vulture decline in India to deadly bacteria spread, causing about 500,000 deaths.",
      "publishedAt": null,
      "title": "Indian vultures: Decline of scavenger birds caused 500,000 human deaths",
      "url": "https://www.bbc.co.uk/news/articles/c28e2pvzn3lo",
      "urlToImage": "https://ichef.bbci.co.uk/news/1024/branded_news/659a/live/791b1120-4a54-11ef-b2d2-cdb23d5d7c5b.jpg"
    },
    {
      "author": "BBC News",
      "description": "Russia intends to destroy dozens of US-built warplanes as soon as they arrive in Ukraine.",
      "publishedAt": null,
      "title": "Ukraine's hopes and challenges after long wait for F16s",
      "url": "https://www.bbc.co.uk/news/articles/c0kr240gd18o",
      "urlToImage": "https://ichef.bbci.co.uk/news/1024/branded_news/2b94/live/cce4bb60-4aab-11ef-aebc-6de4d31bf5cd.jpg"
    },
    {
      "author": "BBC News",
      "description": "Paris is opening the games with an spectacular ceremony. Here's all you need to know.",
      "publishedAt": null,
      "title": "An armchair guide to watching the Olympic opening cermony",
      "url": "https://www.bbc.co.uk/news/articles/cljy547p871o",
      "urlToImage": "https://ichef.bbci.co.uk/news/1024/branded_news/0287/live/c97885b0-48ee-11ef-b74c-bb483a802c97.jpg"
    }
  ],
  "sortBy": "top",
  "source": "bbc-news",
  "status": "ok"
}