{
  "articles": [
    {
      "author": "BBC News",
      "description": "The Israeli and Hamas leaders are suspected of committing war crimes during the continuing war in Gaza.",
      "publishedAt": null,
      "title": "What ICC arrest warrants mean for Israel, Benjamin Netanyahu and Hamas",
      "url": "https://www.bbc.co.uk/news/articles/cw4490z75v3o",
      "urlToImage": "https://ichef.bbci.co.uk/news/1024/branded_news/8a0e/live/a98f9ff0-16f7-11ef-8378-63398510ddfa.jpg"
    },
    {
      "author": "BBC News",
      "description": "The prosecution rested Monday and closing statements are expected to take place next week.",
      "publishedAt": null,
      "title": "Trump trial: Cohen says he stole thousands from company",
      "url": "https://www.bbc.co.uk/news/world-us-canada-69041401",
      "urlToImage": "https://ichef.bbci.co.uk/news/1024/branded_news/CD70/production/_133329525_eb1ac88950b30f7cc61cb7b12dac4c4c812aa41e.jpg"
    },
    {
      "author": "BBC News",
      "description": "On Monday, witness Robert Costello appeared frustrations on the stand, glaring at the judge.",
      "publishedAt": null,
      "title": "Trump trial: Judge reprimands Trump witness over groans",
      "url": "https://www.bbc.co.uk/news/world-us-canada-69041617",
      "urlToImage": "https://ichef.bbci.co.uk/news/1024/branded_news/15628/production/_133329578_6e30bd80448a23fd4482e22a4b26cbece3d2d373-2.jpg"
    },
    {
      "author": "BBC News",
      "description": "The US president criticises the ICC for applying for an arrest warrant for Israel's prime minister.",
      "publishedAt": null,
      "title": "ICC: Biden condemns request for Netanyahu arrest warrant",
      "url": "https://www.bbc.co.uk/news/articles/cmllykpwgdyo",
      "urlToImage": "https://ichef.bbci.co.uk/news/1024/branded_news/baac/live/db6b7600-16d6-11ef-9b12-1ba8f95c4917.jpg"
    },
    {
      "author": "BBC News",
      "description": "The French Pacific territory's airport has been closed since deadly unrest erupted last week.",
      "publishedAt": null,
      "title": "New Caledonia: Australia and New Zealand send evacuation flights amid unrest",
      "url": "https://www.bbc.co.uk/news/articles/crgg821ezz8o",
      "urlToImage": "https://ichef.bbci.co.uk/news/1024/branded_news/c90a/live/591858c0-1713-11ef-b71c-3b126590418b.jpg"
    },
    {
      "author": "BBC News",
      "description": "The group believed that Queen Elizabeth II's death might have been a secret signal to act.",
      "publishedAt": null,
      "title": "Reichsb\u00fcrger group members go on trial over alleged coup",
      "url": "https://www.bbc.co.uk/news/articles/c6pp5g7n866o",
      "urlToImage": "https://ichef.bbci.co.uk/news/1024/branded_news/8fc9/live/9d615580-16dd-11ef-bf4c-d3aa639a5294.jpg"
    },
    {
      "author": "BBC News",
      "description": "The boppy propaganda tune extols Kim Jong Un as a \"friendly father\" and \"great leader\".",
      "publishedAt": null,
      "title": "Friendly Father: South Korea bans TikTok hit idolising Kim Jong Un",
      "url": "https://www.bbc.co.uk/news/articles/cjmmj7r0v2go",
      "urlToImage": "https://ichef.bbci.co.uk/news/1024/branded_news/85cd/live/87c88e60-1713-11ef-b71c-3b126590418b.jpg"
    },
    {
      "author": "BBC News",
      "description": "More than 600 people died in the worst migrant shipwreck in a decade",
      "publishedAt": null,
      "title": "Greek Shipwreck: Concerns over trial of accused",
      "url": "https://www.bbc.co.uk/news/articles/c255njzzx2lo",
      "urlToImage": "https://ichef.bbci.co.uk/news/1024/branded_news/161f/live/1d128f00-16b2-11ef-9b12-1ba8f95c4917.jpg"
    },
    {
      "author": "BBC News",
      "description": "The car makers used parts made by a supplier banned over alleged links to Chinese forced labour.",
      "publishedAt": null,
      "title": "BMW, Jaguar and VW imported banned Xinjiang parts - Senate probe",
      "url": "https://www.bbc.co.uk/news/articles/cv2237rplg8o",
      "urlToImage": "https://ichef.bbci.co.uk/news/1024/branded_news/adf8/live/6718d150-1710-11ef-a762-7f93a78476c3.jpg"
    },
    {
      "author": "BBC News",
      "description": "They dress in traditional clothing every day, own vintage furniture and limit time with technology.",
      "publishedAt": null,
      "title": "Norfolk couple in their 20s live like it is the 1940s",
      "url": "https://www.bbc.co.uk/news/articles/cx030v84l3vo",
      "urlToImage": "https://ichef.bbci.co.uk/news/1024/branded_news/639b/live/f9b170a0-15c9-11ef-9b12-1ba8f95c4917.jpg"
    }
  ],
  "sortBy": "top",
  "source": "bbc-news",
  "status": "ok"
}