{
  "articles": [
    {
      "author": "Andrew Gray, Andrea Shalal",
      "description": "The deal will bring welcome clarity for EU companies though many in Europe will see it as a poor outcome.",
      "publishedAt": "2025-07-27T04:05:26Z",
      "title": "US and EU strike deal with 15% tariff to avert trade war",
      "url": "https://www.reuters.com/business/us-eu-strike-deal-with-15-tariff-avert-trade-war-2025-07-27/",
      "urlToImage": "https://www.reuters.com/resizer/v2/4P64XUXQYFOOLJ6U24PDSPTHSY.jpg?auth=24ef471260d6236a49f28d08a09402ce152bee724c04cd170740625a2b374415&height=1005&width=1920&quality=80&smart=true"
    }
  ],
  "sortBy": "top",
  "source": "reuters",
  "status": "ok"
}